setup.cfg
setup.py
logfetch/__init__.py
logfetch/callbacks.py
logfetch/cat.py
logfetch/entrypoint.py
logfetch/errors.py
logfetch/fake_section_head.py
logfetch/grep.py
logfetch/live_logs.py
logfetch/logfetch_base.py
logfetch/s3_logs.py
logfetch/search.py
logfetch/tail.py
singularity_logfetch.egg-info/PKG-INFO
singularity_logfetch.egg-info/SOURCES.txt
singularity_logfetch.egg-info/dependency_links.txt
singularity_logfetch.egg-info/entry_points.txt
singularity_logfetch.egg-info/not-zip-safe
singularity_logfetch.egg-info/requires.txt
singularity_logfetch.egg-info/top_level.txt