Metadata-Version: 1.0
Name: singularity-logfetch
Version: 0.27.3
Summary: Singularity log fetching and searching
Home-page: https://github.com/HubSpot/Singularity
Author: HubSpot
Author-email: singularity-users@googlegroups.com
License: UNKNOWN
Platform: UNKNOWN
